tokun/__init__.py
tokun/data.py
tokun/eval.py
tokun/huggingface.py
tokun/layers/__init__.py
tokun/layers/dense.py
tokun/losses.py
tokun/metrics.py
tokun/models/__init__.py
tokun/models/klvae.py
tokun/models/vqvae.py
tokun/pipeline/__init__.py
tokun/pipeline/flat/__init__.py
tokun/pipeline/flat/postprocess.py
tokun/pipeline/flat/preprocess.py
tokun/pipeline/hilbert/__init__.py
tokun/pipeline/hilbert/postprocess.py
tokun/pipeline/hilbert/preprocess.py
tokun/pipeline/square/__init__.py
tokun/pipeline/square/postprocess.py
tokun/pipeline/square/preprocess.py
tokun-0.18.0.dist-info/METADATA
tokun-0.18.0.dist-info/WHEEL
tokun-0.18.0.dist-info/RECORD
